clien.py
clienBBS-1.31.dist-info/METADATA
clienBBS-1.31.dist-info/WHEEL
clienBBS-1.31.dist-info/entry_points.txt
clienBBS-1.31.dist-info/top_level.txt
clienBBS-1.31.dist-info/RECORD
