Metadata-Version: 2.1
Name: clienBBS
Version: 1.31
Summary: clienBBS: Retro-style BBS interface for the Clien.net community
Home-page: https://github.com/liza183/clienBBS
Author: Matt Sangkeun Lee
Author-email: johnleespapa@gmail.com
License: Private Use Only
Platform: UNKNOWN
Classifier: Programming Language :: Python
Classifier: Programming Language :: Python :: 3
Classifier: Programming Language :: Python :: 3 :: Only
Requires-Python: >=3.2
Requires-Dist: urllib3
Requires-Dist: bs4
Requires-Dist: certifi
Requires-Dist: requests
Requires-Dist: pyreadline
Requires-Dist: lxml
Requires-Dist: image
